<annotation>
	<folder>Images</folder>
	<filename>dolphin_batch2200005.jpg</filename>
	<path>/home/dan/darkflow/train/Images/dolphin_batch2200005.jpg</path>
	<source>
		<database>Unknown</database>
	</source>
	<size>
		<width>3840</width>
		<height>2160</height>
		<depth>3</depth>
	</size>
	<segmented>0</segmented>
	<object>
		<name>dolphin</name>
		<pose>Unspecified</pose>
		<truncated>0</truncated>
		<difficult>0</difficult>
		<bndbox>
			<xmin>2458</xmin>
			<ymin>1105</ymin>
			<xmax>2560</xmax>
			<ymax>1211</ymax>
		</bndbox>
	</object>
	<object>
		<name>dolphin</name>
		<pose>Unspecified</pose>
		<truncated>0</truncated>
		<difficult>0</difficult>
		<bndbox>
			<xmin>1571</xmin>
			<ymin>869</ymin>
			<xmax>1635</xmax>
			<ymax>982</ymax>
		</bndbox>
	</object>
	<object>
		<name>dolphin</name>
		<pose>Unspecified</pose>
		<truncated>0</truncated>
		<difficult>0</difficult>
		<bndbox>
			<xmin>1611</xmin>
			<ymin>18</ymin>
			<xmax>1703</xmax>
			<ymax>124</ymax>
		</bndbox>
	</object>
</annotation>
