<annotation>
	<folder>Images</folder>
	<filename>dolphin_batch1700018.jpg</filename>
	<path>/home/dan/darkflow/train/Images/dolphin_batch1700018.jpg</path>
	<source>
		<database>Unknown</database>
	</source>
	<size>
		<width>3840</width>
		<height>2160</height>
		<depth>3</depth>
	</size>
	<segmented>0</segmented>
	<object>
		<name>dolphin</name>
		<pose>Unspecified</pose>
		<truncated>0</truncated>
		<difficult>0</difficult>
		<bndbox>
			<xmin>3167</xmin>
			<ymin>1029</ymin>
			<xmax>3304</xmax>
			<ymax>1106</ymax>
		</bndbox>
	</object>
</annotation>
