<annotation>
	<folder>Images</folder>
	<filename>dolphin_batch600030.jpg</filename>
	<path>/home/dan/darkflow/train/Images/dolphin_batch600030.jpg</path>
	<source>
		<database>Unknown</database>
	</source>
	<size>
		<width>4096</width>
		<height>2160</height>
		<depth>3</depth>
	</size>
	<segmented>0</segmented>
	<object>
		<name>dolphin</name>
		<pose>Unspecified</pose>
		<truncated>0</truncated>
		<difficult>0</difficult>
		<bndbox>
			<xmin>2536</xmin>
			<ymin>704</ymin>
			<xmax>2662</xmax>
			<ymax>832</ymax>
		</bndbox>
	</object>
	<object>
		<name>dolphin</name>
		<pose>Unspecified</pose>
		<truncated>0</truncated>
		<difficult>0</difficult>
		<bndbox>
			<xmin>1288</xmin>
			<ymin>1276</ymin>
			<xmax>1418</xmax>
			<ymax>1390</ymax>
		</bndbox>
	</object>
	<object>
		<name>dolphin</name>
		<pose>Unspecified</pose>
		<truncated>0</truncated>
		<difficult>0</difficult>
		<bndbox>
			<xmin>1160</xmin>
			<ymin>1340</ymin>
			<xmax>1256</xmax>
			<ymax>1470</ymax>
		</bndbox>
	</object>
</annotation>
