<annotation>
	<folder>images</folder>
	<filename>surfer_batch1600002.jpg</filename>
	<path>/home/mitch/Desktop/surfer/images/surfer_batch1600002.jpg</path>
	<source>
		<database>Unknown</database>
	</source>
	<size>
		<width>3840</width>
		<height>2160</height>
		<depth>3</depth>
	</size>
	<segmented>0</segmented>
	<object>
		<name>surfer</name>
		<pose>Unspecified</pose>
		<truncated>0</truncated>
		<difficult>0</difficult>
		<bndbox>
			<xmin>2741</xmin>
			<ymin>415</ymin>
			<xmax>2860</xmax>
			<ymax>480</ymax>
		</bndbox>
	</object>
	<object>
		<name>surfer</name>
		<pose>Unspecified</pose>
		<truncated>0</truncated>
		<difficult>0</difficult>
		<bndbox>
			<xmin>2652</xmin>
			<ymin>231</ymin>
			<xmax>2738</xmax>
			<ymax>277</ymax>
		</bndbox>
	</object>
	<object>
		<name>surfer</name>
		<pose>Unspecified</pose>
		<truncated>0</truncated>
		<difficult>0</difficult>
		<bndbox>
			<xmin>2565</xmin>
			<ymin>117</ymin>
			<xmax>2620</xmax>
			<ymax>161</ymax>
		</bndbox>
	</object>
	<object>
		<name>surfer</name>
		<pose>Unspecified</pose>
		<truncated>0</truncated>
		<difficult>0</difficult>
		<bndbox>
			<xmin>2690</xmin>
			<ymin>39</ymin>
			<xmax>2738</xmax>
			<ymax>90</ymax>
		</bndbox>
	</object>
	<object>
		<name>surfer</name>
		<pose>Unspecified</pose>
		<truncated>0</truncated>
		<difficult>0</difficult>
		<bndbox>
			<xmin>2455</xmin>
			<ymin>90</ymin>
			<xmax>2520</xmax>
			<ymax>134</ymax>
		</bndbox>
	</object>
	<object>
		<name>surfer</name>
		<pose>Unspecified</pose>
		<truncated>1</truncated>
		<difficult>0</difficult>
		<bndbox>
			<xmin>2444</xmin>
			<ymin>1</ymin>
			<xmax>2484</xmax>
			<ymax>34</ymax>
		</bndbox>
	</object>
	<object>
		<name>surfer</name>
		<pose>Unspecified</pose>
		<truncated>0</truncated>
		<difficult>0</difficult>
		<bndbox>
			<xmin>2303</xmin>
			<ymin>85</ymin>
			<xmax>2382</xmax>
			<ymax>150</ymax>
		</bndbox>
	</object>
</annotation>
