<annotation>
	<folder>images</folder>
	<filename>surfer_batch900010.jpg</filename>
	<path>/home/mitch/Desktop/surfer/images/surfer_batch900010.jpg</path>
	<source>
		<database>Unknown</database>
	</source>
	<size>
		<width>3840</width>
		<height>2160</height>
		<depth>3</depth>
	</size>
	<segmented>0</segmented>
	<object>
		<name>surfer</name>
		<pose>Unspecified</pose>
		<truncated>0</truncated>
		<difficult>0</difficult>
		<bndbox>
			<xmin>2030</xmin>
			<ymin>2028</ymin>
			<xmax>2095</xmax>
			<ymax>2101</ymax>
		</bndbox>
	</object>
	<object>
		<name>surfer</name>
		<pose>Unspecified</pose>
		<truncated>0</truncated>
		<difficult>0</difficult>
		<bndbox>
			<xmin>2311</xmin>
			<ymin>1612</ymin>
			<xmax>2390</xmax>
			<ymax>1696</ymax>
		</bndbox>
	</object>
	<object>
		<name>surfer</name>
		<pose>Unspecified</pose>
		<truncated>0</truncated>
		<difficult>0</difficult>
		<bndbox>
			<xmin>1679</xmin>
			<ymin>1369</ymin>
			<xmax>1757</xmax>
			<ymax>1517</ymax>
		</bndbox>
	</object>
	<object>
		<name>surfer</name>
		<pose>Unspecified</pose>
		<truncated>0</truncated>
		<difficult>0</difficult>
		<bndbox>
			<xmin>3630</xmin>
			<ymin>617</ymin>
			<xmax>3736</xmax>
			<ymax>715</ymax>
		</bndbox>
	</object>
</annotation>
